Metadata-Version: 2.1
Name: housing_library_5497
Version: 0.1
Summary: Sample code for coding practice
Author-email: yasaswini-ayodhy <yasaswini.ayodhy@tigeranalytics.com>
Project-URL: Homepage, https://github.com/yasaswini-ayodhy/mle-training.git
Keywords: housing,data training
Classifier: Programming Language :: Python :: 3
Requires-Python: >=3.11
Requires-Dist: numpy
Requires-Dist: pandas
Requires-Dist: scikit-learn
